odoo/addons/edi_sale_order_import_ubl/README.rst
odoo/addons/edi_sale_order_import_ubl/__init__.py
odoo/addons/edi_sale_order_import_ubl/__manifest__.py
odoo/addons/edi_sale_order_import_ubl/data/edi_exchange_type.xml
odoo/addons/edi_sale_order_import_ubl/i18n/edi_sale_order_import_ubl.pot
odoo/addons/edi_sale_order_import_ubl/i18n/it.po
odoo/addons/edi_sale_order_import_ubl/readme/CONTRIBUTORS.rst
odoo/addons/edi_sale_order_import_ubl/readme/DESCRIPTION.rst
odoo/addons/edi_sale_order_import_ubl/static/description/icon.png
odoo/addons/edi_sale_order_import_ubl/static/description/index.html
odoo14_addon_edi_sale_order_import_ubl-14.0.1.0.1.dev5.dist-info/METADATA
odoo14_addon_edi_sale_order_import_ubl-14.0.1.0.1.dev5.dist-info/WHEEL
odoo14_addon_edi_sale_order_import_ubl-14.0.1.0.1.dev5.dist-info/top_level.txt
odoo14_addon_edi_sale_order_import_ubl-14.0.1.0.1.dev5.dist-info/RECORD
